[
  {
    "path": "/",
    "name": "主页",
    "key": "dashboard",
    "icon": "dashboard",
    "children": [
      {
        "path": "/",
        "name": "数据分析",
        "key": "Dashboard.Analysis"
      },
      {
        "path": "/dashboard/monitor",
        "name": "数据监控",
        "key": "Dashboard.Monitor"
      },
      {
        "path": "/dashboard/Workplace",
        "name": "工作区",
        "key": "Dashboard.Workplace"
      }
    ]
  },
  {
    "path": "/Nodes",
    "name": "节点",
    "key": "Nodes",
    "icon": "node-index",
    "children": [
      {
        "path": "/Nodes/List",
        "name": "节点列表",
        "key": "Nodes.List"
      },
      {
        "path": "/Nodes/StatusChangeRecords",
        "name": "状态变更记录",
        "key": "Nodes.StatusChangeRecords"
      },
      {
        "path": "/Nodes/Settings",
        "name": "节点设置",
        "key": "Nodes.Settings"
      }
    ]
  },
  {
    "path": "/DataQuality",
    "name": "数据质量",
    "key": "DataQuality",
    "icon": "file-sync",
    "children": [
      {
        "path": "/DataQuality/Calendar",
        "name": "数据质量日历",
        "key": "DataQuality.Calendar"
      },
      {
        "path": "/DataQuality/Statistics",
        "name": "数据质量分析",
        "key": "DataQuality.Statistics"
      },
      {
        "path": "/DataQuality/FileRecords",
        "name": "文件记录",
        "key": "DataQuality.FileRecords"
      },
      {
        "path": "/DataQuality/StatisticsDefinitions",
        "name": "统计定义",
        "key": "DataQuality.StatisticsDefinitions"
      },
      {
        "path": "/DataQuality/Settings",
        "name": "设置",
        "key": "DataQuality.Settings"
      }
    ]
  },
  {
    "path": "/Tasks",
    "name": "任务",
    "key": "Tasks",
    "icon": "schedule",
    "children": [
      {
        "path": "/Tasks/Definitions",
        "name": "任务流定义",
        "key": "Tasks.Definitions"
      },
      {
        "path": "/Tasks/Instances",
        "name": "任务流实例",
        "key": "Tasks.Instances"
      },
      {
        "path": "/Tasks/InstanceGroups",
        "name": "任务流实例分组",
        "key": "Tasks.InstanceGroups"
      }
    ]
  },
  {
    "path": "/CommonConfig",
    "name": "配置",
    "key": "CommonConfig",
    "icon": "setting",
    "children": [
      {
        "path": "/CommonConfig/Database/",
        "name": "数据库配置",
        "key": "CommonConfig.Database"
      },
      {
        "path": "/CommonConfig/Ftp",
        "name": "Ftp配置",
        "key": "CommonConfig.Ftp"
      },
      {
        "path": "/CommonConfig/Kafka",
        "name": "Kafka配置",
        "key": "CommonConfig.Kafka"
      },
      {
        "path": "/CommonConfig/NodeEnvVars",
        "name": "节点环境变量配置",
        "key": "CommonConfig.NodeEnvVars"
      },
      {
        "path": "/CommonConfig/Package",
        "name": "包配置",
        "key": "CommonConfig.Package"
      },
      {
        "path": "/CommonConfig/FtpUpload",
        "name": "Ftp上传配置",
        "key": "CommonConfig.FtpUpload"
      },
      {
        "path": "/CommonConfig/FtpDownload",
        "name": "Ftp下载配置",
        "key": "CommonConfig.FtpDownload"
      },
      {
        "path": "/CommonConfig/RestApi",
        "name": "RestApi配置",
        "key": "CommonConfig.RestApi"
      },
      {
        "path": "/CommonConfig/FileSystemWatch",
        "name": "文件系统监控配置",
        "key": "CommonConfig.FileSystemWatch"
      },
      {
        "path": "/CommonConfig/WindowsTask",
        "name": "Windows计划任务配置",
        "key": "CommonConfig.WindowsTask"
      },
      {
        "path": "/CommonConfig/TaskTypeDesc",
        "name": "作业类型描述配置",
        "key": "CommonConfig.TaskTypeDesc"
      },
      {
        "path": "/CommonConfig/ClientUpdates",
        "name": "客户端更新配置",
        "key": "CommonConfig.ClientUpdates"
      }
    ]
  },
  {
    "path": "/Notifications",
    "name": "订阅与通知",
    "key": "Notifications",
    "icon": "notification",
    "children": [
      {
        "path": "/Notifications/Configure",
        "name": "通知配置",
        "key": "Notifications.Configure"
      },
      {
        "path": "/Notifications/Sources",
        "name": "通知源",
        "key": "Notifications.Sources"
      },
      {
        "path": "/Notifications/Records",
        "name": "通知记录",
        "key": "Notifications.Records"
      }
    ]
  },
  {
    "path": "/Diagnostics",
    "name": "诊断",
    "key": "Diagnostics",
    "icon": "bug",
    "children": [
      {
        "path": "/Diagnostics/MemoryCache",
        "name": "内存缓存",
        "key": "Diagnostics.MemoryCache"
      },
      {
        "path": "/Diagnostics/ExceptionCounter",
        "name": "异常计数器",
        "key": "Diagnostics.ExceptionCounter"
      },
      {
        "path": "/Diagnostics/WebServerCounter",
        "name": "网站计数器",
        "key": "Diagnostics.WebServerCounter"
      }
    ]
  }
]